MANIFEST.in
README.rst
setup.py
docs/HISTORY.txt
docs/LICENSE.GPL
docs/LICENSE.txt
ftw/__init__.py
ftw.book.egg-info/PKG-INFO
ftw.book.egg-info/SOURCES.txt
ftw.book.egg-info/dependency_links.txt
ftw.book.egg-info/entry_points.txt
ftw.book.egg-info/namespace_packages.txt
ftw.book.egg-info/not-zip-safe
ftw.book.egg-info/requires.txt
ftw.book.egg-info/top_level.txt
ftw/book/__init__.py
ftw/book/config.py
ftw/book/configure.zcml
ftw/book/hooks.py
ftw/book/indexers.py
ftw/book/interfaces.py
ftw/book/lawgiver.zcml
ftw/book/migration.py
ftw/book/permissions.py
ftw/book/permissions.zcml
ftw/book/resources.zcml
ftw/book/subscribers.py
ftw/book/testing.py
ftw/book/toc.py
ftw/book/zipexport.py
ftw/book/Extensions/__init__.py
ftw/book/Extensions/install.py
ftw/book/behaviors/__init__.py
ftw/book/behaviors/clearpage.py
ftw/book/behaviors/codeinjection.py
ftw/book/behaviors/columnlayout.py
ftw/book/behaviors/configure.zcml
ftw/book/behaviors/landscape.py
ftw/book/behaviors/toc.py
ftw/book/browser/__init__.py
ftw/book/browser/blockview.py
ftw/book/browser/book_tabs.py
ftw/book/browser/book_view.py
ftw/book/browser/configure.zcml
ftw/book/browser/index_view.py
ftw/book/browser/indexer.py
ftw/book/browser/keywords.py
ftw/book/browser/simplelayout.py
ftw/book/browser/tabbed_book_view.py
ftw/book/browser/table_export_import.py
ftw/book/browser/toc_tree.py
ftw/book/browser/utils.py
ftw/book/browser/reader/__init__.py
ftw/book/browser/reader/configure.zcml
ftw/book/browser/reader/interfaces.py
ftw/book/browser/reader/renderer.py
ftw/book/browser/reader/utils.py
ftw/book/browser/reader/view.py
ftw/book/browser/reader/resources/reader.js
ftw/book/browser/reader/templates/book_title.pt
ftw/book/browser/reader/templates/navigation_recurse.pt
ftw/book/browser/reader/templates/reader.pt
ftw/book/browser/resources/book-compiled.css
ftw/book/browser/resources/book-compiled.js
ftw/book/browser/resources/icon_export_import.png
ftw/book/browser/resources/importexport.svg
ftw/book/browser/resources/keywords.js
ftw/book/browser/resources/main.css
ftw/book/browser/resources/main.js
ftw/book/browser/resources/onegov.scss
ftw/book/browser/resources/table.js
ftw/book/browser/resources/theming.scss
ftw/book/browser/resources/tinymce/footnote-button-plugin.js
