Metadata-Version: 2.1
Name: ftw.book
Version: 4.1.7
Summary: Produce books with Plone and export them in a high quality PDF.
Home-page: https://github.com/4teamwork/ftw.book
Author: 4teamwork AG
Author-email: mailto:info@4teamwork.ch
Maintainer: Jonas Baumann
License: GPL2
Keywords: ftw book pdf plone
Platform: UNKNOWN
Classifier: Framework :: Plone
Classifier: Framework :: Plone :: 4.3
Classifier: Framework :: Plone :: 5.1
Classifier: Intended Audience :: Developers
Classifier: Topic :: Software Development :: Libraries :: Python Modules
Provides-Extra: tests
Provides-Extra: tabbeview
Provides-Extra: linguaplone
